drhip/__init__.py
drhip/cli.py
drhip/config.py
drhip/version.py
drhip/methods/__init__.py
drhip/methods/base.py
drhip/methods/busted.py
drhip/methods/cfel.py
drhip/methods/fel.py
drhip/methods/meme.py
drhip/methods/prime.py
drhip/methods/registry.py
drhip/methods/relax.py
drhip/parsers/__init__.py
drhip/parsers/process_gene.py
drhip/utils/__init__.py
drhip/utils/file_handlers.py
drhip/utils/result_helpers.py
drhip/utils/sequence_utils.py
drhip/utils/tree_helpers.py
drhip-0.1.4.dist-info/LICENSE
drhip-0.1.4.dist-info/METADATA
drhip-0.1.4.dist-info/WHEEL
drhip-0.1.4.dist-info/entry_points.txt
drhip-0.1.4.dist-info/top_level.txt
drhip-0.1.4.dist-info/RECORD
