Metadata-Version: 2.1
Name: drhip
Version: 0.1.4
Summary: DRHIP: Data Reduction for HyPhy with Inference Processing - A toolkit for analyzing and summarizing HyPhy evolutionary selection analysis results
Home-page: https://github.com/veg/drhip
Author: Danielle Callan, Hannah Verdonk, Sergei L Kosakovsky Pond
Author-email: spond@temple.edu
Project-URL: Bug Reports, https://github.com/veg/drhip/issues
Project-URL: Source, https://github.com/veg/drhip
Classifier: Development Status :: 4 - Beta
Classifier: Intended Audience :: Science/Research
Classifier: Topic :: Scientific/Engineering :: Bio-Informatics
Classifier: Programming Language :: Python :: 3.7
Classifier: Programming Language :: Python :: 3.8
Classifier: Programming Language :: Python :: 3.9
Classifier: Programming Language :: Python :: 3.10
Classifier: License :: OSI Approved :: MIT License
Classifier: Operating System :: OS Independent
Requires-Python: >=3.7
License-File: LICENSE
Requires-Dist: numpy>=1.20.0
Requires-Dist: pandas>=1.3.0
Requires-Dist: scipy>=1.7.0
Provides-Extra: dev
Requires-Dist: pytest>=7.0.0; extra == "dev"
Requires-Dist: pytest-cov>=4.0.0; extra == "dev"
Requires-Dist: pre-commit>=3.0.0; extra == "dev"
Requires-Dist: black>=24.0.0; extra == "dev"
Requires-Dist: isort>=5.12.0; extra == "dev"
Requires-Dist: ruff>=0.1.0; extra == "dev"
